ci_agents/__init__.py
ci_agents/context_manage.py
ci_agents/factory.py
ci_agents/hub_agent.py
ci_agents/hub_agents_with_communicate.py
ci_agents/infra_agent.py
ci_agents/infra_agent_fake_test.py
ci_agents/lab_agent.py
ci_agents/log_config.py
ci_agents/runner.py
ci_agents/script_bug_agent.py
ci_agents/types.py
hooks/__init__.py
hooks/agent_hook_log.py
hooks/hub_hook_context.py
hooks/run_hook_log.py
langfuse/__init__.py
langfuse/langfuse_config.py
langfuse/langfuse_decorate.py
ci_analysis_agents-0.1.13.dist-info/METADATA
ci_analysis_agents-0.1.13.dist-info/WHEEL
ci_analysis_agents-0.1.13.dist-info/top_level.txt
ci_analysis_agents-0.1.13.dist-info/RECORD
