Metadata-Version: 2.4
Name: ci-analysis-agents
Version: 0.1.13
Summary: A Python project to call OpenAI Agents to analyze CI logs.
Author-email: Jennifer Huang <jennifer.huang@ringcentral.com>
Requires-Python: <4.0,>=3.11
Requires-Dist: openai==1.79.0
Requires-Dist: openai-agents==0.0.15
Requires-Dist: requests==2.32.3
Requires-Dist: annotated-types==0.7.0
Requires-Dist: anyio==4.9.0
Requires-Dist: certifi==2025.1.31
Requires-Dist: charset-normalizer==3.4.1
Requires-Dist: click==8.1.8
Requires-Dist: colorama==0.4.6
Requires-Dist: distro==1.9.0
Requires-Dist: griffe==1.7.2
Requires-Dist: h11==0.14.0
Requires-Dist: httpcore==1.0.7
Requires-Dist: httpx==0.28.1
Requires-Dist: httpx-sse==0.4.0
Requires-Dist: idna==3.10
Requires-Dist: jiter==0.9.0
Requires-Dist: mcp==1.9.0
Requires-Dist: pydantic==2.11.3
Requires-Dist: pydantic-settings==2.8.1
Requires-Dist: pydantic-core==2.33.1
Requires-Dist: python-dotenv==1.1.0
Requires-Dist: sniffio==1.3.1
Requires-Dist: sse-starlette==2.2.1
Requires-Dist: starlette==0.46.1
Requires-Dist: tqdm==4.67.1
Requires-Dist: types-requests==2.32.0.20250328
Requires-Dist: typing-inspection==0.4.0
Requires-Dist: typing-extensions==4.13.2
Requires-Dist: urllib3==2.4.0
Requires-Dist: uvicorn==0.34.0
Requires-Dist: anthropic==0.51.0
Requires-Dist: argcomplete==3.6.2
Requires-Dist: boto3==1.38.18
Requires-Dist: botocore==1.38.18
Requires-Dist: cachetools==5.5.2
Requires-Dist: cohere==5.15.0
Requires-Dist: deprecated==1.2.18
Requires-Dist: eval-type-backport==0.2.2
Requires-Dist: executing==2.2.0
Requires-Dist: fasta2a==0.2.3
Requires-Dist: fastavro==1.10.0
Requires-Dist: filelock==3.18.0
Requires-Dist: fsspec==2025.3.2
Requires-Dist: google-auth==2.40.1
Requires-Dist: googleapis-common-protos==1.70.0
Requires-Dist: groq==0.25.0
Requires-Dist: huggingface-hub==0.31.2
Requires-Dist: importlib-metadata==8.6.1
Requires-Dist: iniconfig==2.1.0
Requires-Dist: jmespath==1.0.1
Requires-Dist: logfire==3.16.0
Requires-Dist: logfire-api==3.16.0
Requires-Dist: markdown-it-py==3.0.0
Requires-Dist: mdurl==0.1.2
Requires-Dist: mistralai==1.7.0
Requires-Dist: nest-asyncio==1.6.0
Requires-Dist: opentelemetry-api==1.33.1
Requires-Dist: opentelemetry-exporter-otlp-proto-common==1.33.1
Requires-Dist: opentelemetry-exporter-otlp-proto-http==1.33.1
Requires-Dist: opentelemetry-instrumentation==0.54b1
Requires-Dist: opentelemetry-proto==1.33.1
Requires-Dist: opentelemetry-sdk==1.33.1
Requires-Dist: opentelemetry-semantic-conventions==0.54b1
Requires-Dist: packaging==24.2
Requires-Dist: pluggy==1.5.0
Requires-Dist: prompt-toolkit==3.0.51
Requires-Dist: protobuf==5.29.4
Requires-Dist: pyasn1==0.6.1
Requires-Dist: pyasn1-modules==0.4.2
Requires-Dist: pydantic-ai==0.2.3
Requires-Dist: pydantic-ai-slim==0.2.3
Requires-Dist: pydantic-evals==0.2.3
Requires-Dist: pydantic-graph==0.2.3
Requires-Dist: pygments==2.19.1
Requires-Dist: pytest==8.3.5
Requires-Dist: pytest-asyncio==0.26.0
Requires-Dist: python-dateutil==2.9.0.post0
Requires-Dist: pyyaml==6.0.2
Requires-Dist: rich==14.0.0
Requires-Dist: rsa==4.9.1
Requires-Dist: s3transfer==0.12.0
Requires-Dist: six==1.17.0
Requires-Dist: tokenizers==0.21.1
Requires-Dist: wcwidth==0.2.13
Requires-Dist: wrapt==1.17.2
Requires-Dist: zipp==3.21.0
Requires-Dist: backoff==2.2.1
Requires-Dist: backports-tarfile==1.2.0
Requires-Dist: docutils==0.21.2
Requires-Dist: id==1.5.0
Requires-Dist: jaraco-classes==3.4.0
Requires-Dist: jaraco-context==6.0.1
Requires-Dist: jaraco-functools==4.1.0
Requires-Dist: keyring==25.6.0
Requires-Dist: langfuse==2.60.5
Requires-Dist: more-itertools==10.7.0
Requires-Dist: nh3==0.2.21
Requires-Dist: python-multipart==0.0.20
Requires-Dist: readme-renderer==44.0
Requires-Dist: requests-toolbelt==1.0.0
Requires-Dist: rfc3986==2.0.0
Requires-Dist: twine==6.1.0
